{"path":"551847.jpg","date":"September 1973","photographer":"Okamoto, Yoichi R.","caption":"This photograph captures a vibrant street scene, likely taken in a European city. The central figure is a man in traditional attire, possibly German, characterized by a dark waistcoat with green accents, a white shirt, and black trousers. He is balding, wears glasses and balances two full steins of beer in his hands, one in each. His poised yet casual demeanor suggests he is used to carrying such a load, possibly a waiter or at a beer festival.\n\nBehind him, the street bustles with people. Two women are walking towards the camera; one in a red sweater and blue jeans, the other in a plaid shirt and darker pants. The rest of the crowd varies in age and dress, reflecting a casual, everyday setting. \n\nThe architecture suggests a shopping or commercial area, with store fronts running along the street seen in the background, and an overhanging structure on the left that might be part of a cafe or restaurant extending towards the sidewalk.\n\nThe photograph has a slight blur suggesting motion, and the soft lighting and shadows indicate it might be midday or early afternoon. The overall atmosphere is lively and public, with a sense of community engagement typical of urban European settings.","title":"Munich's large and beautiful Fussgängerzone (pedestrian zone) has returned the city's commercial and cultural center to the people. It is totally traffic free. Not even bicycle riding is permitted. Beer is a popular beverage in this outdoor mall.","placename":"Munich (Germany)","location":"Munich, Germany","nn1":["551874","551871","551790","551789","557802","551849","551816","557656","557803","551788","551840","551829","551806","558265","557663","558266"],"cl":[36],"cluster":["#36 &mdash; Street"],"terms":["beer","street","cafe","poise","restaurant","festival","shopping","overhang","midday","accent"]}
